preview_generator/__init__.py
preview_generator/exception.py
preview_generator/file_converter.py
preview_generator/manager.py
preview_generator/utils.py
preview_generator/preview/__init__.py
preview_generator/preview/builder_factory.py
preview_generator/preview/generic_preview.py
preview_generator/preview/builder/__init__.py
preview_generator/preview/builder/archive__zip.py
preview_generator/preview/builder/image__inkscape.py
preview_generator/preview/builder/image__pillow.py
preview_generator/preview/builder/image__wand.py
preview_generator/preview/builder/office__libreoffice.py
preview_generator/preview/builder/pdf__pypdf2.py
preview_generator/preview/builder/plain_text.py
preview_generator-0.2.2.dist-info/DESCRIPTION.rst
preview_generator-0.2.2.dist-info/METADATA
preview_generator-0.2.2.dist-info/RECORD
preview_generator-0.2.2.dist-info/WHEEL
preview_generator-0.2.2.dist-info/metadata.json
preview_generator-0.2.2.dist-info/top_level.txt
tests/__init__.py
tests/deprecatedtest_eps_input.py
tests/test_builder_factory.py
tests/test_manager.py
tests/test_utils.py
tests/input/__init__.py
tests/input/image.py
tests/input/bmp/__init__.py
tests/input/bmp/test_bmp.py
tests/input/eps/__init__.py
tests/input/eps/test_eps.py
tests/input/gif/__init__.py
tests/input/gif/test_gif.py
tests/input/jpeg/__init__.py
tests/input/jpeg/test_jpeg.py
tests/input/odt/__init__.py
tests/input/odt/test_odt.py
tests/input/pdf/__init__.py
tests/input/pdf/test_pdf.py
tests/input/png/__init__.py
tests/input/png/test_png.py
tests/input/txt/__init__.py
tests/input/txt/test_txt.py
tests/input/zip/__init__.py
tests/input/zip/test_zip.py
