Metadata-Version: 1.2
Name: preview_generator
Version: 0.2.2
Summary: A library for generating preview (thumbnails, text or json overview) for file-based content
Home-page: https://github.com/algoo/preview-generator
Author: Algoo
Author-email: contact@algoo.fr
License: UNKNOWN
Download-URL: https://github.com/algoo/preview-generator/archive/0.2.2.tar.gz
Keywords: preview,preview_generator,thumbnail,cache
Platform: UNKNOWN
Classifier: Programming Language :: Python :: 3.4
Classifier: Programming Language :: Python :: 3.5
Classifier: Programming Language :: Python :: 3.6
Requires-Python: >= 3.4
